setup.cfg
setup.py
xintian/__init__.py
xintian/db.py
xintian/exception.py
xintian/server.py
xintian/utils.py
xintian.egg-info/PKG-INFO
xintian.egg-info/SOURCES.txt
xintian.egg-info/dependency_links.txt
xintian.egg-info/requires.txt
xintian.egg-info/top_level.txt