Metadata-Version: 1.0
Name: xintian
Version: 0.0.6
Summary: A micro service framework for Sanic, so easy.
Home-page: https://github.com/huangxinping/xintian
Author: huangxinping
Author-email: o0402@outlook.com
License: MIT
Keywords: micro,service,sanic,flask
Platform: UNKNOWN
